datasette_enrichments_shell/__init__.py
datasette_enrichments_shell/cli.py
datasette_enrichments_shell/enrichment.py
datasette_enrichments_shell-0.3.0.dist-info/METADATA
datasette_enrichments_shell-0.3.0.dist-info/WHEEL
datasette_enrichments_shell-0.3.0.dist-info/entry_points.txt
datasette_enrichments_shell-0.3.0.dist-info/RECORD
