Metadata-Version: 2.1
Name: datasette-enrichments-shell
Version: 0.3.0
Summary: Enrich data using datasette and arbitrary commands on your local machine
License: MIT
Keywords: datasette,datasette-enrichments,shell,sqlite
Author: Michael Bianco
Author-email: mike@mikebian.co
Requires-Python: >=3.9,<4.0
Classifier: Framework :: Datasette
Classifier: License :: OSI Approved :: Apache Software License
Classifier: License :: OSI Approved :: MIT License
Classifier: Programming Language :: Python :: 3
Classifier: Programming Language :: Python :: 3.9
Classifier: Programming Language :: Python :: 3.10
Classifier: Programming Language :: Python :: 3.11
Classifier: Programming Language :: Python :: 3.12
Requires-Dist: datasette (>=0.64.6,<0.65.0)
Requires-Dist: datasette-enrichments (>=0.2,<0.5)
Requires-Dist: sqlite-utils (>=3.36,<4.0)
Project-URL: Changelog, https://github.com/iloveitaly/datasette-enrichments-shell/releases
Project-URL: CI, https://github.com/iloveitaly/datasette-enrichments-shell/actions
Project-URL: Homepage, https://github.com/iloveitaly/datasette-enrichments-shell
Project-URL: Issues, https://github.com/iloveitaly/datasette-enrichments-shell/issues
